treetool/__init__.py
treetool/seg_tree.py
treetool/tree_tool.py
treetool/utils.py
treetool-1.0.1.dist-info/LICENSE
treetool-1.0.1.dist-info/METADATA
treetool-1.0.1.dist-info/WHEEL
treetool-1.0.1.dist-info/top_level.txt
treetool-1.0.1.dist-info/RECORD
